<annotation>
	<folder></folder>
	<filename>IMG20240621221920_jpg.rf.a483779647890de450f3dfb4201e61c6.jpg</filename>
	<path>IMG20240621221920_jpg.rf.a483779647890de450f3dfb4201e61c6.jpg</path>
	<source>
		<database>roboflow.com</database>
	</source>
	<size>
		<width>320</width>
		<height>320</height>
		<depth>3</depth>
	</size>
	<segmented>0</segmented>
	<object>
		<name>Senang</name>
		<pose>Unspecified</pose>
		<truncated>0</truncated>
		<difficult>0</difficult>
		<occluded>0</occluded>
		<bndbox>
			<xmin>101</xmin>
			<xmax>248</xmax>
			<ymin>129</ymin>
			<ymax>225</ymax>
		</bndbox>
	</object>
</annotation>
